evodex/__init__.py
evodex/allyltrp.py
evodex/astatine.py
evodex/decofactor.py
evodex/evaluation.py
evodex/formula.py
evodex/hydrogen_mapper.py
evodex/mass_spec.py
evodex/mechanistic_labeler.py
evodex/operators.py
evodex/projection.py
evodex/projection_map.py
evodex/splitting.py
evodex/synthesis.py
evodex/utils.py
evodex/data/EVODEX-B.csv
evodex/data/EVODEX-Bm.csv
evodex/data/EVODEX-C.csv
evodex/data/EVODEX-Cm.csv
evodex/data/EVODEX-D.csv
evodex/data/EVODEX-D_synthesis_subset.csv
evodex/data/EVODEX-Dm.csv
evodex/data/EVODEX-E.csv
evodex/data/EVODEX-Em.csv
evodex/data/EVODEX-F.csv
evodex/data/EVODEX-M.csv
evodex/data/EVODEX-M_mass_spec_subset.csv
evodex/data/EVODEX-P.csv
evodex/data/EVODEX-R.csv
evodex/data/selected_reactions.csv
evodex-2.0.1.dist-info/licenses/LICENSE
evodex-2.0.1.dist-info/METADATA
evodex-2.0.1.dist-info/WHEEL
evodex-2.0.1.dist-info/top_level.txt
evodex-2.0.1.dist-info/RECORD
