Metadata-Version: 2.4
Name: evodex
Version: 2.0.1
Summary: A project to process enzymatic reactions
Home-page: https://github.com/jcaucb/evodex
Author: J. Christopher Anderson
Author-email: jcanderson@berkeley.edu
Classifier: Programming Language :: Python :: 3
Classifier: License :: OSI Approved :: MIT License
Classifier: Operating System :: OS Independent
Requires-Python: >=3.6
License-File: LICENSE
Requires-Dist: rdkit
Requires-Dist: pandas
Requires-Dist: numpy
Dynamic: author
Dynamic: author-email
Dynamic: classifier
Dynamic: description
Dynamic: description-content-type
Dynamic: home-page
Dynamic: license-file
Dynamic: requires-dist
Dynamic: requires-python
Dynamic: summary
